CHANGELOG
MANIFEST.in
README
distribute_setup.py
pkg_utils.py
setup.cfg
setup.py
doc/README
doc/conf.py
doc/debugging.rst
doc/index.rst
doc/libref.rst
doc/tutorial.rst
doc/_static/empty
doc/_templates/empty
doc/examples/infix_precedence.rst
modgrammar/__init__.py
modgrammar/debugging.py
modgrammar/extras.py
modgrammar/util.py
modgrammar.egg-info/PKG-INFO
modgrammar.egg-info/SOURCES.txt
modgrammar.egg-info/dependency_links.txt
modgrammar.egg-info/top_level.txt
modgrammar.egg-info/zip-safe
modgrammar/examples/__init__.py
modgrammar/examples/infix_precedence.py
tests/__init__.py
tests/__main__.py
tests/basic_grammar.py
tests/debugging.py
tests/parsing.py
tests/regression.py
tests/unicode.py
tests/util.py
tests/whitespace.py
tests/whitespace_mode.py
tests/ref_tests/__init__.py
tests/ref_tests/basic_resolve_refs.py
tests/ref_tests/follow_norecurse_resolve_refs.py
tests/ref_tests/follow_resolve_refs.py
tests/ref_tests/general_tests.py
tests/ref_tests/norecurse_resolve_refs.py