Metadata-Version: 1.1
Name: modgrammar
Version: 0.10
Summary: Modular grammar-parsing engine
Home-page: http://code.google.com/p/modgrammar
Author: Alex Stewart
Author-email: alex@foogod.com
License: BSD
Download-URL: http://pypi.python.org/pypi/modgrammar
Platform: any
Classifier: Development Status :: 4 - Beta
Classifier: Intended Audience :: Developers
Classifier: License :: OSI Approved :: BSD License
Classifier: Operating System :: OS Independent
Classifier: Programming Language :: Python
Classifier: Programming Language :: Python :: 3
Classifier: Programming Language :: Python :: 3.1
Classifier: Programming Language :: Python :: 3.2
Classifier: Topic :: Text Processing
Classifier: Topic :: Software Development :: Libraries :: Python Modules
